<annotation>
	<folder>titleist</folder>
	<filename>titleist.8f2c7e4a-c51f-11ee-ba8e-244bfe93b879.jpg</filename>
	<path>C:\Users\Jonathan Rönnäs\Tprog\Tensorflow Object detection\TFODCourse\Tensorflow\workspace\images\collectedimages\titleist\titleist.8f2c7e4a-c51f-11ee-ba8e-244bfe93b879.jpg</path>
	<source>
		<database>Unknown</database>
	</source>
	<size>
		<width>640</width>
		<height>480</height>
		<depth>3</depth>
	</size>
	<segmented>0</segmented>
	<object>
		<name>Ball</name>
		<pose>Unspecified</pose>
		<truncated>0</truncated>
		<difficult>0</difficult>
		<bndbox>
			<xmin>85</xmin>
			<ymin>139</ymin>
			<xmax>317</xmax>
			<ymax>371</ymax>
		</bndbox>
	</object>
	<object>
		<name>Titleist</name>
		<pose>Unspecified</pose>
		<truncated>0</truncated>
		<difficult>0</difficult>
		<bndbox>
			<xmin>164</xmin>
			<ymin>185</ymin>
			<xmax>243</xmax>
			<ymax>261</ymax>
		</bndbox>
	</object>
</annotation>
